qcp_omics/__init__.py
qcp_omics/cli/__init__.py
qcp_omics/cli/__pycache__/__init__.cpython-311.pyc
qcp_omics/cli/cli.py
qcp_omics/cli/handle_execution.py
qcp_omics/cli/input_validation.py
qcp_omics/cli/interactive.py
qcp_omics/cli/metadata.py
qcp_omics/mixins/__init__.py
qcp_omics/mixins/analysis_mixin.py
qcp_omics/mixins/preprocessing_mixin.py
qcp_omics/mixins/qc_mixin.py
qcp_omics/mixins/visualization_mixin.py
qcp_omics/models/__init__.py
qcp_omics/models/clinical_data.py
qcp_omics/models/genomics_data.py
qcp_omics/models/omics_data.py
qcp_omics/models/proteomics_data.py
qcp_omics/report_generation/__init__.py
qcp_omics/report_generation/generate_report.py
qcp_omics/report_generation/report_step.py
qcp_omics/report_generation/templates/analysis/descriptive_statistics.jinja
qcp_omics/report_generation/templates/analysis/evaluate_distribution_features.jinja
qcp_omics/report_generation/templates/analysis/pairwise_correlations_numerical.jinja
qcp_omics/report_generation/templates/common/step.jinja
qcp_omics/report_generation/templates/common/table_view.jinja
qcp_omics/report_generation/templates/preprocessing/dimensionality_reduction.jinja
qcp_omics/report_generation/templates/preprocessing/scale_features.jinja
qcp_omics/report_generation/templates/preprocessing/split_num_cat.jinja
qcp_omics/report_generation/templates/preprocessing/split_train_test.jinja
qcp_omics/report_generation/templates/preprocessing/transform_features.jinja
qcp_omics/report_generation/templates/quality_control/handle_missing_values.jinja
qcp_omics/report_generation/templates/quality_control/handle_outliers.jinja
qcp_omics/report_generation/templates/quality_control/identify_missing_values.jinja
qcp_omics/report_generation/templates/report_template.jinja
qcp_omics/utils/__init__.py
qcp_omics/utils/protocols.py
qcp_omics/utils/utils.py
qcp_omics-0.2.3.dist-info/LICENSE
qcp_omics-0.2.3.dist-info/METADATA
qcp_omics-0.2.3.dist-info/WHEEL
qcp_omics-0.2.3.dist-info/entry_points.txt
qcp_omics-0.2.3.dist-info/RECORD
