Metadata-Version: 2.3
Name: qcp-omics
Version: 0.2.3
Summary: Quality control, preprocessing and analysis of omics data for machine learning
License: MIT
Author: Georgy Lepsaya
Author-email: georgelepsaya@gmail.com
Requires-Python: >=3.11,<4.0
Classifier: License :: OSI Approved :: MIT License
Classifier: Programming Language :: Python :: 3
Classifier: Programming Language :: Python :: 3.11
Classifier: Programming Language :: Python :: 3.12
Classifier: Programming Language :: Python :: 3.13
Requires-Dist: click (>=8.1.7,<9.0.0)
Requires-Dist: jinja2 (>=3.1.4,<4.0.0)
Requires-Dist: pandas (>=2.2.3,<3.0.0)
Requires-Dist: plotly (>=5.24.1,<6.0.0)
Requires-Dist: pydantic (>=2.10.2,<3.0.0)
Requires-Dist: scikit-learn (>=1.6.0,<2.0.0)
